inducoapi/__init__.py
inducoapi/__main__.py
inducoapi/inducoapi.py
inducoapi-2.1.11.dist-info/LICENSE
inducoapi-2.1.11.dist-info/METADATA
inducoapi-2.1.11.dist-info/WHEEL
inducoapi-2.1.11.dist-info/entry_points.txt
inducoapi-2.1.11.dist-info/RECORD
