Metadata-Version: 2.3
Name: inducoapi
Version: 2.1.11
Summary: A simple python program to generate OpenApi documentation by supplying request/response bodies.
License: Apache-2.0
Keywords: openapi,rest
Author: Matteo Pergolesi
Author-email: matpergo@gmail.com
Requires-Python: >=3.9.0,<3.14
Classifier: License :: OSI Approved :: Apache Software License
Classifier: Programming Language :: Python :: 3
Classifier: Programming Language :: Python :: 3.9
Classifier: Programming Language :: Python :: 3.10
Classifier: Programming Language :: Python :: 3.11
Classifier: Programming Language :: Python :: 3.12
Classifier: Programming Language :: Python :: 3.13
Requires-Dist: openapi-spec-validator (>=0.7,<0.8)
Requires-Dist: pyyaml (>=6.0,<7.0)
Project-URL: Homepage, https://github.com/TheWall89/inducoapi
Project-URL: Repository, https://github.com/TheWall89/inducoapi
